{
    "name": "American Nurseryman. vol 199, no. 6. (2004)",
    "machine_name": "american_nurseryman_vol_199_no_6_2004",
    "type": "journal_book",
    "volume": null,
    "number": null,
    "year": "2004",
    "additional_info": null,
    "publish_date": null,
    "pulling_date": null,
    "description": null,
    "archival_data": {
        "id": "2118945",
        "legacy_id": "56992",
        "author": "oitadmin",
        "created": "1473951107"
    },
    "citation_reference_items": [
        {
            "name": "American Nurseryman. vol 199, no. 6. (2004) p 10",
            "machine_name": "american_nurseryman_vol_199_no_6_2004_p_10",
            "type": "citation_reference",
            "plant": {
                "machine_name": "epimedium_cultivars_crimson",
                "type": "variety",
                "archival_data": [
                    "1588031"
                ]
            },
            "volume": null,
            "page": "p 10",
            "year": "2004",
            "notes": null,
            "parts_shown": {
                "Flower": true,
                "Seed": false,
                "Fruit": false,
                "Bark": false,
                "Root": false,
                "Habit": true,
                "Leaf": false,
                "Twig": false,
                "Unclear": false
            },
            "citation_type": {
                "Art": false,
                "Photo": false
            },
            "archival_data": {
                "id": "1919478",
                "legacy_id": "275106",
                "AD": false,
                "fpi_pub_issue": null,
                "pullingdat": "7",
                "active": true,
                "author": "oitadmin",
                "created": "1483186869"
            }
        },
        {
            "name": "American Nurseryman. vol 199, no. 6. (2004) p 12",
            "machine_name": "american_nurseryman_vol_199_no_6_2004_p_12",
            "type": "citation_reference",
            "plant": {
                "machine_name": "hosta_cultivars_sum_and_substance",
                "type": "variety",
                "archival_data": [
                    "1480276"
                ]
            },
            "volume": null,
            "page": "p 12",
            "year": "2004",
            "notes": null,
            "parts_shown": {
                "Flower": false,
                "Seed": false,
                "Fruit": false,
                "Bark": false,
                "Root": false,
                "Habit": true,
                "Leaf": false,
                "Twig": false,
                "Unclear": false
            },
            "citation_type": {
                "Art": false,
                "Photo": false
            },
            "archival_data": {
                "id": "1919479",
                "legacy_id": "275107",
                "AD": false,
                "fpi_pub_issue": null,
                "pullingdat": "7",
                "active": true,
                "author": "oitadmin",
                "created": "1483186869"
            }
        },
        {
            "name": "American Nurseryman. vol 199, no. 6. (2004) p 15 (Adv.)",
            "machine_name": "american_nurseryman_vol_199_no_6_2004_p_15_adv",
            "type": "citation_reference",
            "plant": {
                "machine_name": "thuja_cultivars_steeplechase",
                "type": "variety",
                "archival_data": [
                    "1588029"
                ]
            },
            "volume": null,
            "page": "p 15 (Adv.)",
            "year": "2004",
            "notes": null,
            "parts_shown": {
                "Flower": false,
                "Seed": false,
                "Fruit": false,
                "Bark": false,
                "Root": false,
                "Habit": true,
                "Leaf": false,
                "Twig": false,
                "Unclear": false
            },
            "citation_type": {
                "Art": false,
                "Photo": false
            },
            "archival_data": {
                "id": "1919480",
                "legacy_id": "275108",
                "AD": false,
                "fpi_pub_issue": null,
                "pullingdat": "7",
                "active": true,
                "author": "oitadmin",
                "created": "1483186869"
            }
        },
        {
            "name": "American Nurseryman. vol 199, no. 6. (2004) p 15 (Adv.)",
            "machine_name": "american_nurseryman_vol_199_no_6_2004_p_15_adv",
            "type": "citation_reference",
            "plant": {
                "machine_name": "cornus_kousa_wolf_eyes",
                "type": "variety",
                "archival_data": [
                    "1501769"
                ]
            },
            "volume": null,
            "page": "p 15 (Adv.)",
            "year": "2004",
            "notes": null,
            "parts_shown": {
                "Flower": false,
                "Seed": false,
                "Fruit": false,
                "Bark": false,
                "Root": false,
                "Habit": false,
                "Leaf": true,
                "Twig": false,
                "Unclear": false
            },
            "citation_type": {
                "Art": false,
                "Photo": false
            },
            "archival_data": {
                "id": "1919481",
                "legacy_id": "275109",
                "AD": false,
                "fpi_pub_issue": null,
                "pullingdat": "7",
                "active": true,
                "author": "oitadmin",
                "created": "1483186869"
            }
        },
        {
            "name": "American Nurseryman. vol 199, no. 6. (2004) p 31 (Adv.)",
            "machine_name": "american_nurseryman_vol_199_no_6_2004_p_31_adv",
            "type": "citation_reference",
            "plant": {
                "machine_name": "magnolia_grandiflora_claudia_wannamaker",
                "type": "variety",
                "archival_data": [
                    "1518010"
                ]
            },
            "volume": null,
            "page": "p 31 (Adv.)",
            "year": "2004",
            "notes": null,
            "parts_shown": {
                "Flower": false,
                "Seed": false,
                "Fruit": false,
                "Bark": false,
                "Root": false,
                "Habit": true,
                "Leaf": false,
                "Twig": false,
                "Unclear": false
            },
            "citation_type": {
                "Art": false,
                "Photo": false
            },
            "archival_data": {
                "id": "1919482",
                "legacy_id": "275110",
                "AD": false,
                "fpi_pub_issue": null,
                "pullingdat": "7",
                "active": true,
                "author": "oitadmin",
                "created": "1483186869"
            }
        },
        {
            "name": "American Nurseryman. vol 199, no. 6. (2004) p 35",
            "machine_name": "american_nurseryman_vol_199_no_6_2004_p_35",
            "type": "citation_reference",
            "plant": {
                "machine_name": "itea_virginica_little_henry",
                "type": "variety",
                "archival_data": [
                    "1533129"
                ]
            },
            "volume": null,
            "page": "p 35",
            "year": "2004",
            "notes": null,
            "parts_shown": {
                "Flower": false,
                "Seed": false,
                "Fruit": false,
                "Bark": false,
                "Root": false,
                "Habit": true,
                "Leaf": false,
                "Twig": false,
                "Unclear": false
            },
            "citation_type": {
                "Art": false,
                "Photo": false
            },
            "archival_data": {
                "id": "1919483",
                "legacy_id": "275111",
                "AD": false,
                "fpi_pub_issue": null,
                "pullingdat": "7",
                "active": true,
                "author": "oitadmin",
                "created": "1483186869"
            }
        },
        {
            "name": "American Nurseryman. vol 199, no. 6. (2004) p 35",
            "machine_name": "american_nurseryman_vol_199_no_6_2004_p_35",
            "type": "citation_reference",
            "plant": {
                "machine_name": "sambucus_racemosa_sutherland_gold",
                "type": "variety",
                "archival_data": [
                    "1491272"
                ]
            },
            "volume": null,
            "page": "p 35",
            "year": "2004",
            "notes": null,
            "parts_shown": {
                "Flower": false,
                "Seed": false,
                "Fruit": false,
                "Bark": false,
                "Root": false,
                "Habit": true,
                "Leaf": false,
                "Twig": false,
                "Unclear": false
            },
            "citation_type": {
                "Art": false,
                "Photo": false
            },
            "archival_data": {
                "id": "1919484",
                "legacy_id": "275112",
                "AD": false,
                "fpi_pub_issue": null,
                "pullingdat": "7",
                "active": true,
                "author": "oitadmin",
                "created": "1483186869"
            }
        },
        {
            "name": "American Nurseryman. vol 199, no. 6. (2004) p 35",
            "machine_name": "american_nurseryman_vol_199_no_6_2004_p_35",
            "type": "citation_reference",
            "plant": {
                "machine_name": "sambucus_nigra_black_beauty",
                "type": "variety",
                "archival_data": [
                    "1534229"
                ]
            },
            "volume": null,
            "page": "p 35",
            "year": "2004",
            "notes": null,
            "parts_shown": {
                "Flower": false,
                "Seed": false,
                "Fruit": false,
                "Bark": false,
                "Root": false,
                "Habit": true,
                "Leaf": false,
                "Twig": false,
                "Unclear": false
            },
            "citation_type": {
                "Art": false,
                "Photo": false
            },
            "archival_data": {
                "id": "1919485",
                "legacy_id": "275113",
                "AD": false,
                "fpi_pub_issue": null,
                "pullingdat": "7",
                "active": true,
                "author": "oitadmin",
                "created": "1483186869"
            }
        },
        {
            "name": "American Nurseryman. vol 199, no. 6. (2004) p 38 (Adv.)",
            "machine_name": "american_nurseryman_vol_199_no_6_2004_p_38_adv",
            "type": "citation_reference",
            "plant": {
                "machine_name": "styrax_japonicus_snowcone",
                "type": "variety",
                "archival_data": [
                    "1562150"
                ]
            },
            "volume": null,
            "page": "p 38 (Adv.)",
            "year": "2004",
            "notes": null,
            "parts_shown": {
                "Flower": true,
                "Seed": false,
                "Fruit": false,
                "Bark": false,
                "Root": false,
                "Habit": true,
                "Leaf": false,
                "Twig": false,
                "Unclear": false
            },
            "citation_type": {
                "Art": false,
                "Photo": false
            },
            "archival_data": {
                "id": "1919486",
                "legacy_id": "275114",
                "AD": false,
                "fpi_pub_issue": null,
                "pullingdat": "7",
                "active": true,
                "author": "oitadmin",
                "created": "1483186869"
            }
        },
        {
            "name": "American Nurseryman. vol 199, no. 6. (2004) p 40",
            "machine_name": "american_nurseryman_vol_199_no_6_2004_p_40",
            "type": "citation_reference",
            "plant": {
                "machine_name": "hibiscus_syriacus_chiffon_series",
                "type": "variety",
                "archival_data": [
                    "1548625"
                ]
            },
            "volume": null,
            "page": "p 40",
            "year": "2004",
            "notes": null,
            "parts_shown": {
                "Flower": false,
                "Seed": false,
                "Fruit": false,
                "Bark": false,
                "Root": false,
                "Habit": true,
                "Leaf": false,
                "Twig": false,
                "Unclear": false
            },
            "citation_type": {
                "Art": false,
                "Photo": false
            },
            "archival_data": {
                "id": "1919487",
                "legacy_id": "275115",
                "AD": false,
                "fpi_pub_issue": null,
                "pullingdat": "7",
                "active": true,
                "author": "oitadmin",
                "created": "1483186869"
            }
        },
        {
            "name": "American Nurseryman. vol 199, no. 6. (2004) p 94",
            "machine_name": "american_nurseryman_vol_199_no_6_2004_p_94",
            "type": "citation_reference",
            "plant": {
                "machine_name": "gunnera_manicata",
                "type": "species",
                "archival_data": [
                    "1414252"
                ]
            },
            "volume": null,
            "page": "p 94",
            "year": "2004",
            "notes": null,
            "parts_shown": {
                "Flower": false,
                "Seed": false,
                "Fruit": false,
                "Bark": false,
                "Root": false,
                "Habit": true,
                "Leaf": true,
                "Twig": false,
                "Unclear": false
            },
            "citation_type": {
                "Art": false,
                "Photo": false
            },
            "archival_data": {
                "id": "1919488",
                "legacy_id": "275116",
                "AD": false,
                "fpi_pub_issue": null,
                "pullingdat": "7",
                "active": true,
                "author": "oitadmin",
                "created": "1483186869"
            }
        }
    ]
}
