{
    "name": "American Conifer Society, Bulletin. vol 18, no. 2. (2001)",
    "machine_name": "american_conifer_society_bulletin_vol_18_no_2_2001",
    "type": "journal_book",
    "volume": null,
    "number": null,
    "year": "2001",
    "additional_info": null,
    "publish_date": null,
    "pulling_date": null,
    "description": null,
    "archival_data": {
        "id": "2116958",
        "legacy_id": "23190",
        "author": "oitadmin",
        "created": "1473951107"
    },
    "citation_reference_items": [
        {
            "name": "American Conifer Society, Bulletin. vol 18, no. 2. (2001) p inside cover",
            "machine_name": "american_conifer_society_bulletin_vol_18_no_2_2001_p_inside_cover",
            "type": "citation_reference",
            "plant": {
                "machine_name": "juniperus_pfitzeriana_wilhelm_pfitzer",
                "type": "variety",
                "archival_data": [
                    "1556106"
                ]
            },
            "volume": null,
            "page": "p inside cover",
            "year": "2001",
            "notes": null,
            "parts_shown": {
                "Flower": false,
                "Seed": false,
                "Fruit": false,
                "Bark": false,
                "Root": false,
                "Habit": true,
                "Leaf": false,
                "Twig": false,
                "Unclear": false
            },
            "citation_type": {
                "Art": false,
                "Photo": false
            },
            "archival_data": {
                "id": "1881234",
                "legacy_id": "209331",
                "AD": false,
                "fpi_pub_issue": null,
                "pullingdat": "7",
                "active": true,
                "author": "oitadmin",
                "created": "1483180383"
            }
        },
        {
            "name": "American Conifer Society, Bulletin. vol 18, no. 2. (2001) p inside backcover",
            "machine_name": "american_conifer_society_bulletin_vol_18_no_2_2001_p_inside_backcover",
            "type": "citation_reference",
            "plant": {
                "machine_name": "juniperus_procumbens_nana_kishiogima",
                "type": "variety",
                "archival_data": [
                    "1564064"
                ]
            },
            "volume": null,
            "page": "p inside backcover",
            "year": "2001",
            "notes": null,
            "parts_shown": {
                "Flower": false,
                "Seed": false,
                "Fruit": false,
                "Bark": false,
                "Root": false,
                "Habit": true,
                "Leaf": false,
                "Twig": false,
                "Unclear": false
            },
            "citation_type": {
                "Art": false,
                "Photo": false
            },
            "archival_data": {
                "id": "1881235",
                "legacy_id": "209332",
                "AD": false,
                "fpi_pub_issue": null,
                "pullingdat": "7",
                "active": true,
                "author": "oitadmin",
                "created": "1483180383"
            }
        },
        {
            "name": "American Conifer Society, Bulletin. vol 18, no. 2. (2001) p backcover",
            "machine_name": "american_conifer_society_bulletin_vol_18_no_2_2001_p_backcover",
            "type": "citation_reference",
            "plant": {
                "machine_name": "picea_glauca_jean_s_dilly",
                "type": "variety",
                "archival_data": [
                    "1521419"
                ]
            },
            "volume": null,
            "page": "p backcover",
            "year": "2001",
            "notes": null,
            "parts_shown": {
                "Flower": false,
                "Seed": false,
                "Fruit": false,
                "Bark": false,
                "Root": false,
                "Habit": true,
                "Leaf": false,
                "Twig": false,
                "Unclear": false
            },
            "citation_type": {
                "Art": false,
                "Photo": false
            },
            "archival_data": {
                "id": "1881236",
                "legacy_id": "209333",
                "AD": false,
                "fpi_pub_issue": null,
                "pullingdat": "7",
                "active": true,
                "author": "oitadmin",
                "created": "1483180383"
            }
        }
    ]
}
